cv2/LICENSE.txt
cv2/__init__.py
cv2/cv2.cpython-34m.so
opencv_python_aarch64-3.3.0.1.dist-info/DESCRIPTION.rst
opencv_python_aarch64-3.3.0.1.dist-info/METADATA
opencv_python_aarch64-3.3.0.1.dist-info/RECORD
opencv_python_aarch64-3.3.0.1.dist-info/WHEEL
opencv_python_aarch64-3.3.0.1.dist-info/metadata.json
opencv_python_aarch64-3.3.0.1.dist-info/top_level.txt
